[
 {
  "id": "AeHIrLTr6JkxGE6SN-0Rw",
  "name": "Allen Raymond",
  "email": "nulla.ante@vestibul.co.uk",
  "phone": "(992) 914-3792"
 },
 {
  "id": "qdggE76Jtbfd9eWJHrssH",
  "name": "Chaim Lewis",
  "email": "dui.in@egetlacus.ca",
  "phone": "(294) 840-6685"
 },
 {
  "id": "drsAJ4SHPYqZeG-83QTVW",
  "name": "Kennedy Lane",
  "email": "mattis.Cras@nonenimMauris.net",
  "phone": "(542) 451-7038"
 },
 {
  "id": "vza2RIzNGIwutCVCs4mCL",
  "name": "Wylie Pope",
  "email": "est@utquamvel.net",
  "phone": "(692) 802-2949"
 },
 {
  "id": "05olLMgyVQdWRwgKfg5J6",
  "name": "Cyrus Jackson",
  "email": "nibh@semsempererat.com",
  "phone": "(501) 472-5218"
 },
 {
  "id": "1DEXoP8AuCGYc1YgoQ6hw",
  "name": "Abbot Franks",
  "email": "scelerisque@magnis.org",
  "phone": "(186) 568-3720"
 },
 {
  "id": "Z5sbDlS7pCzNsnAHLtDJd",
  "name": "Reuben Henry",
  "email": "pharetra.ut@dictum.co.uk",
  "phone": "(715) 598-5792"
 },
 {
  "id": "C9sjBfCo4UJCWjzBnOtxl",
  "name": "Simon Morton",
  "email": "dui.Fusce.diam@Donec.com",
  "phone": "(233) 738-2360"
 },
 {
  "id": "e6ywwRe4jcqxXfCZOj_1e",
  "name": "Thomas Lucas",
  "email": "nec@Nulla.com",
  "phone": "(704) 398-7993"
 },
 {
  "id": "rsKkOQUi80UsgVPCcLZZW",
  "name": "Alec Howard",
  "email": "Donec.elementum@scelerisquescelerisquedui.net",
  "phone": "(748) 206-2688"
 },
 {
  "id": "qdggE76Jtbfd9eWJHrssH",
  "name": "1111111111",
  "email": "11111111@egetlacus.ca",
  "phone": "(111)1111115"
 },
 {
  "id": "EiKke6zczXQCY4Qpgb1kX",
  "name": "999",
  "email": "33333@egetlacus.ca",
  "phone": "(111)1111115"
 },
 {
  "id": "DiqaORAcPvYP5LGaLuKvh",
  "email": "33333@egetlacus.ca",
  "phone": "(111)1111115"
 },
 {
  "id": "rwxM3M1DygtOCwsxAxTWg",
  "email": "33333@egetlacus.ca",
  "phone": "(111)1111115"
 },
 {
  "id": "sD8An9QyJ_u0Gu6_8SjnL",
  "name": "555",
  "email": "33333@egetlacus.ca",
  "phone": "(111)1111115"
 },
 {
  "id": "Bl50Cu7eCUprOvsqIZGOq",
  "email": "33333@egetlacus.ca",
  "phone": "(111)1111115"
 },
 {
  "id": "S13WjkzSMVn1S9WheNTko",
  "name": "1111111111",
  "email": "555@egetlacus.ca",
  "phone": "(111)1111115"
 },
 {
  "id": "xRJ_lcfWRMRHwgYmie5kQ",
  "email": "555@egetlacus.ca",
  "phone": "(111)1111115"
 }
]